{
    "1": {
        "1": {
            "Artist": "Bob Geldof",
            "Song": "This Is The World Calling"
        },
        "2": {
            "Artist": "Bruce Springsteen & The E Street Band",
            "Song": "War (Live)"
        },
        "3": {
            "Artist": "a-ha",
            "Song": "Cry Wolf"
        },
        "4": {
            "Artist": "Bon Jovi",
            "Song": "Livin' On A Prayer"
        },
        "5": {
            "Artist": "Falco",
            "Song": "Coming Home (Jeanny Part 2, ein Jahr danach)"
        },
        "6": {
            "Artist": "Red Box",
            "Song": "For America"
        },
        "7": {
            "Artist": "Duran Duran",
            "Song": "Notorious"
        },
        "8": {
            "Artist": "Alison Moyet",
            "Song": "Is This Love?"
        },
        "9": {
            "Artist": "Cutting Crew",
            "Song": "(I Just) Died In Your Arms"
        },
        "10": {
            "Artist": "Status Quo",
            "Song": "In The Army Now"
        }
    },
    "2": {
        "1": {
            "Artist": "Bob Geldof",
            "Song": "This Is The World Calling"
        },
        "2": {
            "Artist": "Bruce Springsteen & The E Street Band",
            "Song": "War (Live)"
        },
        "3": {
            "Artist": "a-ha",
            "Song": "Cry Wolf"
        },
        "4": {
            "Artist": "Bon Jovi",
            "Song": "Livin' On A Prayer"
        },
        "5": {
            "Artist": "Falco",
            "Song": "Coming Home (Jeanny Part 2, ein Jahr danach)"
        },
        "6": {
            "Artist": "Red Box",
            "Song": "For America"
        },
        "7": {
            "Artist": "Duran Duran",
            "Song": "Notorious"
        },
        "8": {
            "Artist": "Alison Moyet",
            "Song": "Is This Love?"
        },
        "9": {
            "Artist": "Cutting Crew",
            "Song": "(I Just) Died In Your Arms"
        },
        "10": {
            "Artist": "Status Quo",
            "Song": "In The Army Now"
        }
    },
    "3": {
        "1": {
            "Artist": "Bon Jovi",
            "Song": "Livin' On A Prayer"
        },
        "2": {
            "Artist": "a-ha",
            "Song": "Cry Wolf"
        },
        "3": {
            "Artist": "Red Box",
            "Song": "For America"
        },
        "4": {
            "Artist": "Falco",
            "Song": "Coming Home (Jeanny Part 2, ein Jahr danach)"
        },
        "5": {
            "Artist": "Alison Moyet",
            "Song": "Is This Love?"
        },
        "6": {
            "Artist": "Bob Geldof",
            "Song": "This Is The World Calling"
        },
        "7": {
            "Artist": "Bruce Springsteen & The E Street Band",
            "Song": "War (Live)"
        },
        "8": {
            "Artist": "Kim Wilde",
            "Song": "You Keep Me Hangin' On"
        },
        "9": {
            "Artist": "Duran Duran",
            "Song": "Notorious"
        },
        "10": {
            "Artist": "Cutting Crew",
            "Song": "(I Just) Died In Your Arms"
        }
    },
    "4": {
        "1": {
            "Artist": "Bon Jovi",
            "Song": "Livin' On A Prayer"
        },
        "2": {
            "Artist": "Red Box",
            "Song": "For America"
        },
        "3": {
            "Artist": "Alison Moyet",
            "Song": "Is This Love?"
        },
        "4": {
            "Artist": "Falco",
            "Song": "Coming Home (Jeanny Part 2, ein Jahr danach)"
        },
        "5": {
            "Artist": "Kim Wilde",
            "Song": "You Keep Me Hangin' On"
        },
        "6": {
            "Artist": "Bruce Springsteen & The E Street Band",
            "Song": "War (Live)"
        },
        "7": {
            "Artist": "The Housemartins",
            "Song": "Caravan Of Love"
        },
        "8": {
            "Artist": "a-ha",
            "Song": "Cry Wolf"
        },
        "9": {
            "Artist": "Gary Moore",
            "Song": "Over The Hills And Far Away"
        },
        "10": {
            "Artist": "Bob Geldof",
            "Song": "This Is The World Calling"
        }
    },
    "5": {
        "1": {
            "Artist": "Bon Jovi",
            "Song": "Livin' On A Prayer"
        },
        "2": {
            "Artist": "Red Box",
            "Song": "For America"
        },
        "3": {
            "Artist": "Kim Wilde",
            "Song": "You Keep Me Hangin' On"
        },
        "4": {
            "Artist": "Alison Moyet",
            "Song": "Is This Love?"
        },
        "5": {
            "Artist": "The Housemartins",
            "Song": "Caravan Of Love"
        },
        "6": {
            "Artist": "Falco",
            "Song": "Coming Home (Jeanny Part 2, ein Jahr danach)"
        },
        "7": {
            "Artist": "Gary Moore",
            "Song": "Over The Hills And Far Away"
        },
        "8": {
            "Artist": "a-ha",
            "Song": "Cry Wolf"
        },
        "9": {
            "Artist": "Robbie Nevil",
            "Song": "C'est la vie"
        },
        "10": {
            "Artist": "Scotch",
            "Song": "Money Runner"
        }
    },
    "6": {
        "1": {
            "Artist": "Kim Wilde",
            "Song": "You Keep Me Hangin' On"
        },
        "2": {
            "Artist": "Bon Jovi",
            "Song": "Livin' On A Prayer"
        },
        "3": {
            "Artist": "Red Box",
            "Song": "For America"
        },
        "4": {
            "Artist": "The Housemartins",
            "Song": "Caravan Of Love"
        },
        "5": {
            "Artist": "Gary Moore",
            "Song": "Over The Hills And Far Away"
        },
        "6": {
            "Artist": "Alison Moyet",
            "Song": "Is This Love?"
        },
        "7": {
            "Artist": "Jackie Wilson",
            "Song": "Reet Petite"
        },
        "8": {
            "Artist": "Falco",
            "Song": "Coming Home (Jeanny Part 2, ein Jahr danach)"
        },
        "9": {
            "Artist": "Stéphanie",
            "Song": "Live Your Life"
        },
        "10": {
            "Artist": "Aretha Franklin & George Michael",
            "Song": "I Knew You Were Waiting (For Me)"
        }
    },
    "7": {
        "1": {
            "Artist": "Kim Wilde",
            "Song": "You Keep Me Hangin' On"
        },
        "2": {
            "Artist": "Gary Moore",
            "Song": "Over The Hills And Far Away"
        },
        "3": {
            "Artist": "Red Box",
            "Song": "For America"
        },
        "4": {
            "Artist": "The Housemartins",
            "Song": "Caravan Of Love"
        },
        "5": {
            "Artist": "Bon Jovi",
            "Song": "Livin' On A Prayer"
        },
        "6": {
            "Artist": "Alison Moyet",
            "Song": "Is This Love?"
        },
        "7": {
            "Artist": "Jackie Wilson",
            "Song": "Reet Petite"
        },
        "8": {
            "Artist": "Robbie Nevil",
            "Song": "C'est la vie"
        },
        "9": {
            "Artist": "Fahrenheit 104",
            "Song": "Highway To Freedom"
        },
        "10": {
            "Artist": "Falco",
            "Song": "Coming Home (Jeanny Part 2, ein Jahr danach)"
        }
    },
    "8": {
        "1": {
            "Artist": "Kim Wilde",
            "Song": "You Keep Me Hangin' On"
        },
        "2": {
            "Artist": "Gary Moore",
            "Song": "Over The Hills And Far Away"
        },
        "3": {
            "Artist": "The Housemartins",
            "Song": "Caravan Of Love"
        },
        "4": {
            "Artist": "Red Box",
            "Song": "For America"
        },
        "5": {
            "Artist": "Jackie Wilson",
            "Song": "Reet Petite"
        },
        "6": {
            "Artist": "Fahrenheit 104",
            "Song": "Highway To Freedom"
        },
        "7": {
            "Artist": "Robbie Nevil",
            "Song": "C'est la vie"
        },
        "8": {
            "Artist": "Pepsi & Shirlie",
            "Song": "Heartache"
        },
        "9": {
            "Artist": "Bon Jovi",
            "Song": "Livin' On A Prayer"
        },
        "10": {
            "Artist": "Aretha Franklin & George Michael",
            "Song": "I Knew You Were Waiting (For Me)"
        }
    },
    "9": {
        "1": {
            "Artist": "Gary Moore",
            "Song": "Over The Hills And Far Away"
        },
        "2": {
            "Artist": "Kim Wilde",
            "Song": "You Keep Me Hangin' On"
        },
        "3": {
            "Artist": "The Housemartins",
            "Song": "Caravan Of Love"
        },
        "4": {
            "Artist": "Robbie Nevil",
            "Song": "C'est la vie"
        },
        "5": {
            "Artist": "Jackie Wilson",
            "Song": "Reet Petite"
        },
        "6": {
            "Artist": "Red Box",
            "Song": "For America"
        },
        "7": {
            "Artist": "Pepsi & Shirlie",
            "Song": "Heartache"
        },
        "8": {
            "Artist": "Fahrenheit 104",
            "Song": "Highway To Freedom"
        },
        "9": {
            "Artist": "Aretha Franklin & George Michael",
            "Song": "I Knew You Were Waiting (For Me)"
        },
        "10": {
            "Artist": "Level 42",
            "Song": "Running In The Family"
        }
    },
    "10": {
        "1": {
            "Artist": "Gary Moore",
            "Song": "Over The Hills And Far Away"
        },
        "2": {
            "Artist": "Kim Wilde",
            "Song": "You Keep Me Hangin' On"
        },
        "3": {
            "Artist": "The Housemartins",
            "Song": "Caravan Of Love"
        },
        "4": {
            "Artist": "Fahrenheit 104",
            "Song": "Highway To Freedom"
        },
        "5": {
            "Artist": "Robbie Nevil",
            "Song": "C'est la vie"
        },
        "6": {
            "Artist": "Jackie Wilson",
            "Song": "Reet Petite"
        },
        "7": {
            "Artist": "Aretha Franklin & George Michael",
            "Song": "I Knew You Were Waiting (For Me)"
        },
        "8": {
            "Artist": "Pepsi & Shirlie",
            "Song": "Heartache"
        },
        "9": {
            "Artist": "a-ha",
            "Song": "Manhattan Skyline"
        },
        "10": {
            "Artist": "Level 42",
            "Song": "Running In The Family"
        }
    },
    "11": {
        "1": {
            "Artist": "Gary Moore",
            "Song": "Over The Hills And Far Away"
        },
        "2": {
            "Artist": "The Housemartins",
            "Song": "Caravan Of Love"
        },
        "3": {
            "Artist": "Kim Wilde",
            "Song": "You Keep Me Hangin' On"
        },
        "4": {
            "Artist": "Aretha Franklin & George Michael",
            "Song": "I Knew You Were Waiting (For Me)"
        },
        "5": {
            "Artist": "Fahrenheit 104",
            "Song": "Highway To Freedom"
        },
        "6": {
            "Artist": "a-ha",
            "Song": "Manhattan Skyline"
        },
        "7": {
            "Artist": "Pepsi & Shirlie",
            "Song": "Heartache"
        },
        "8": {
            "Artist": "Level 42",
            "Song": "Running In The Family"
        },
        "9": {
            "Artist": "Robbie Nevil",
            "Song": "C'est la vie"
        },
        "10": {
            "Artist": "Jackie Wilson",
            "Song": "Reet Petite"
        }
    },
    "12": {
        "1": {
            "Artist": "Gary Moore",
            "Song": "Over The Hills And Far Away"
        },
        "2": {
            "Artist": "The Housemartins",
            "Song": "Caravan Of Love"
        },
        "3": {
            "Artist": "Fahrenheit 104",
            "Song": "Highway To Freedom"
        },
        "4": {
            "Artist": "a-ha",
            "Song": "Manhattan Skyline"
        },
        "5": {
            "Artist": "Kim Wilde",
            "Song": "You Keep Me Hangin' On"
        },
        "6": {
            "Artist": "Pepsi & Shirlie",
            "Song": "Heartache"
        },
        "7": {
            "Artist": "Aretha Franklin & George Michael",
            "Song": "I Knew You Were Waiting (For Me)"
        },
        "8": {
            "Artist": "Level 42",
            "Song": "Running In The Family"
        },
        "9": {
            "Artist": "Alison Moyet",
            "Song": "Weak In The Presence Of Beauty"
        },
        "10": {
            "Artist": "Robbie Nevil",
            "Song": "C'est la vie"
        }
    },
    "13": {
        "1": {
            "Artist": "Gary Moore",
            "Song": "Over The Hills And Far Away"
        },
        "2": {
            "Artist": "Fahrenheit 104",
            "Song": "Highway To Freedom"
        },
        "3": {
            "Artist": "The Housemartins",
            "Song": "Caravan Of Love"
        },
        "4": {
            "Artist": "Alison Moyet",
            "Song": "Weak In The Presence Of Beauty"
        },
        "5": {
            "Artist": "Boy George",
            "Song": "Everything I Own"
        },
        "6": {
            "Artist": "Pepsi & Shirlie",
            "Song": "Heartache"
        },
        "7": {
            "Artist": "Level 42",
            "Song": "Running In The Family"
        },
        "8": {
            "Artist": "Starship",
            "Song": "Nothing's Gonna Stop Us Now"
        },
        "9": {
            "Artist": "Bryan Adams",
            "Song": "Heat Of The Night"
        },
        "10": {
            "Artist": "a-ha",
            "Song": "Manhattan Skyline"
        }
    },
    "14": {
        "1": {
            "Artist": "Gary Moore",
            "Song": "Over The Hills And Far Away"
        },
        "2": {
            "Artist": "Boy George",
            "Song": "Everything I Own"
        },
        "3": {
            "Artist": "Fahrenheit 104",
            "Song": "Highway To Freedom"
        },
        "4": {
            "Artist": "Starship",
            "Song": "Nothing's Gonna Stop Us Now"
        },
        "5": {
            "Artist": "Alison Moyet",
            "Song": "Weak In The Presence Of Beauty"
        },
        "6": {
            "Artist": "Pepsi & Shirlie",
            "Song": "Heartache"
        },
        "7": {
            "Artist": "Bryan Adams",
            "Song": "Heat Of The Night"
        },
        "8": {
            "Artist": "The Housemartins",
            "Song": "Caravan Of Love"
        },
        "9": {
            "Artist": "Ben E. King",
            "Song": "Stand By Me"
        },
        "10": {
            "Artist": "Mel & Kim",
            "Song": "Respectable"
        }
    },
    "15": {
        "1": {
            "Artist": "Gary Moore",
            "Song": "Over The Hills And Far Away"
        },
        "2": {
            "Artist": "Starship",
            "Song": "Nothing's Gonna Stop Us Now"
        },
        "3": {
            "Artist": "Boy George",
            "Song": "Everything I Own"
        },
        "4": {
            "Artist": "Mel & Kim",
            "Song": "Respectable"
        },
        "5": {
            "Artist": "Fahrenheit 104",
            "Song": "Highway To Freedom"
        },
        "6": {
            "Artist": "Bryan Adams",
            "Song": "Heat Of The Night"
        },
        "7": {
            "Artist": "Alison Moyet",
            "Song": "Weak In The Presence Of Beauty"
        },
        "8": {
            "Artist": "Mental As Anything",
            "Song": "Live It Up"
        },
        "9": {
            "Artist": "Pepsi & Shirlie",
            "Song": "Heartache"
        },
        "10": {
            "Artist": "Prince",
            "Song": "Sign \"&#9774;\" The Times"
        }
    },
    "16": {
        "1": {
            "Artist": "Boy George",
            "Song": "Everything I Own"
        },
        "2": {
            "Artist": "Mel & Kim",
            "Song": "Respectable"
        },
        "3": {
            "Artist": "Starship",
            "Song": "Nothing's Gonna Stop Us Now"
        },
        "4": {
            "Artist": "Ferry Aid",
            "Song": "Let It Be"
        },
        "5": {
            "Artist": "Gary Moore",
            "Song": "Over The Hills And Far Away"
        },
        "6": {
            "Artist": "Mental As Anything",
            "Song": "Live It Up"
        },
        "7": {
            "Artist": "Bryan Adams",
            "Song": "Heat Of The Night"
        },
        "8": {
            "Artist": "Prince",
            "Song": "Sign \"&#9774;\" The Times"
        },
        "9": {
            "Artist": "Fahrenheit 104",
            "Song": "Highway To Freedom"
        },
        "10": {
            "Artist": "Alison Moyet",
            "Song": "Weak In The Presence Of Beauty"
        }
    },
    "17": {
        "1": {
            "Artist": "Boy George",
            "Song": "Everything I Own"
        },
        "2": {
            "Artist": "Mel & Kim",
            "Song": "Respectable"
        },
        "3": {
            "Artist": "Starship",
            "Song": "Nothing's Gonna Stop Us Now"
        },
        "4": {
            "Artist": "Ferry Aid",
            "Song": "Let It Be"
        },
        "5": {
            "Artist": "Gary Moore",
            "Song": "Over The Hills And Far Away"
        },
        "6": {
            "Artist": "Mental As Anything",
            "Song": "Live It Up"
        },
        "7": {
            "Artist": "Bryan Adams",
            "Song": "Heat Of The Night"
        },
        "8": {
            "Artist": "Prince",
            "Song": "Sign \"&#9774;\" The Times"
        },
        "9": {
            "Artist": "Fahrenheit 104",
            "Song": "Highway To Freedom"
        },
        "10": {
            "Artist": "Alison Moyet",
            "Song": "Weak In The Presence Of Beauty"
        }
    },
    "18": {
        "1": {
            "Artist": "Ferry Aid",
            "Song": "Let It Be"
        },
        "2": {
            "Artist": "Mel & Kim",
            "Song": "Respectable"
        },
        "3": {
            "Artist": "Starship",
            "Song": "Nothing's Gonna Stop Us Now"
        },
        "4": {
            "Artist": "Mental As Anything",
            "Song": "Live It Up"
        },
        "5": {
            "Artist": "Boy George",
            "Song": "Everything I Own"
        },
        "6": {
            "Artist": "Fahrenheit 104",
            "Song": "Highway To Freedom"
        },
        "7": {
            "Artist": "Madonna",
            "Song": "La isla bonita"
        },
        "8": {
            "Artist": "Prince",
            "Song": "Sign \"&#9774;\" The Times"
        },
        "9": {
            "Artist": "Richenel",
            "Song": "Dance Around The World"
        }
    },
    "19": {
        "1": {
            "Artist": "Ferry Aid",
            "Song": "Let It Be"
        },
        "2": {
            "Artist": "Mel & Kim",
            "Song": "Respectable"
        },
        "3": {
            "Artist": "Starship",
            "Song": "Nothing's Gonna Stop Us Now"
        },
        "4": {
            "Artist": "Mental As Anything",
            "Song": "Live It Up"
        },
        "5": {
            "Artist": "Madonna",
            "Song": "La isla bonita"
        },
        "6": {
            "Artist": "Boy George",
            "Song": "Everything I Own"
        },
        "7": {
            "Artist": "Prince",
            "Song": "Sign \"&#9774;\" The Times"
        },
        "8": {
            "Artist": "Fahrenheit 104",
            "Song": "Highway To Freedom"
        },
        "9": {
            "Artist": "TNT",
            "Song": "10,000 Lovers (In One)"
        },
        "10": {
            "Artist": "Mandy",
            "Song": "I Just Can't Wait"
        }
    },
    "20": {
        "1": {
            "Artist": "Ferry Aid",
            "Song": "Let It Be"
        },
        "2": {
            "Artist": "Starship",
            "Song": "Nothing's Gonna Stop Us Now"
        },
        "3": {
            "Artist": "Mel & Kim",
            "Song": "Respectable"
        },
        "4": {
            "Artist": "Mental As Anything",
            "Song": "Live It Up"
        },
        "5": {
            "Artist": "Whitney Houston",
            "Song": "I Wanna Dance With Somebody (Who Loves Me)"
        },
        "6": {
            "Artist": "TNT",
            "Song": "10,000 Lovers (In One)"
        },
        "7": {
            "Artist": "Madonna",
            "Song": "La isla bonita"
        },
        "8": {
            "Artist": "Prince",
            "Song": "Sign \"&#9774;\" The Times"
        },
        "9": {
            "Artist": "Mandy",
            "Song": "I Just Can't Wait"
        },
        "10": {
            "Artist": "Living In A Box",
            "Song": "Living In A Box"
        }
    },
    "21": {
        "1": {
            "Artist": "Ferry Aid",
            "Song": "Let It Be"
        },
        "2": {
            "Artist": "Whitney Houston",
            "Song": "I Wanna Dance With Somebody (Who Loves Me)"
        },
        "3": {
            "Artist": "Starship",
            "Song": "Nothing's Gonna Stop Us Now"
        },
        "4": {
            "Artist": "Mental As Anything",
            "Song": "Live It Up"
        },
        "5": {
            "Artist": "TNT",
            "Song": "10,000 Lovers (In One)"
        },
        "6": {
            "Artist": "Mel & Kim",
            "Song": "Respectable"
        },
        "7": {
            "Artist": "Madonna",
            "Song": "La isla bonita"
        },
        "8": {
            "Artist": "Living In A Box",
            "Song": "Living In A Box"
        },
        "9": {
            "Artist": "Prince",
            "Song": "Sign \"&#9774;\" The Times"
        },
        "10": {
            "Artist": "Boy George",
            "Song": "Everything I Own"
        }
    },
    "22": {
        "1": {
            "Artist": "Whitney Houston",
            "Song": "I Wanna Dance With Somebody (Who Loves Me)"
        },
        "2": {
            "Artist": "Ferry Aid",
            "Song": "Let It Be"
        },
        "3": {
            "Artist": "TNT",
            "Song": "10,000 Lovers (In One)"
        },
        "4": {
            "Artist": "Starship",
            "Song": "Nothing's Gonna Stop Us Now"
        },
        "5": {
            "Artist": "Mental As Anything",
            "Song": "Live It Up"
        },
        "6": {
            "Artist": "Madonna",
            "Song": "La isla bonita"
        },
        "7": {
            "Artist": "Living In A Box",
            "Song": "Living In A Box"
        },
        "8": {
            "Artist": "Mel & Kim",
            "Song": "Respectable"
        },
        "9": {
            "Artist": "Boy George",
            "Song": "Everything I Own"
        },
        "10": {
            "Artist": "Johnny Logan",
            "Song": "Hold Me Now"
        }
    },
    "23": {
        "1": {
            "Artist": "Whitney Houston",
            "Song": "I Wanna Dance With Somebody (Who Loves Me)"
        },
        "2": {
            "Artist": "Ferry Aid",
            "Song": "Let It Be"
        },
        "3": {
            "Artist": "TNT",
            "Song": "10,000 Lovers (In One)"
        },
        "4": {
            "Artist": "Starship",
            "Song": "Nothing's Gonna Stop Us Now"
        },
        "5": {
            "Artist": "Mental As Anything",
            "Song": "Live It Up"
        },
        "6": {
            "Artist": "Madonna",
            "Song": "La isla bonita"
        },
        "7": {
            "Artist": "Living In A Box",
            "Song": "Living In A Box"
        },
        "8": {
            "Artist": "Mel & Kim",
            "Song": "Respectable"
        },
        "9": {
            "Artist": "Boy George",
            "Song": "Everything I Own"
        },
        "10": {
            "Artist": "Johnny Logan",
            "Song": "Hold Me Now"
        }
    },
    "24": {
        "1": {
            "Artist": "Whitney Houston",
            "Song": "I Wanna Dance With Somebody (Who Loves Me)"
        },
        "2": {
            "Artist": "Ferry Aid",
            "Song": "Let It Be"
        },
        "3": {
            "Artist": "TNT",
            "Song": "10,000 Lovers (In One)"
        },
        "4": {
            "Artist": "Mental As Anything",
            "Song": "Live It Up"
        },
        "5": {
            "Artist": "Johnny Logan",
            "Song": "Hold Me Now"
        },
        "6": {
            "Artist": "George Michael",
            "Song": "I Want Your Sex"
        },
        "7": {
            "Artist": "Samantha Fox",
            "Song": "Nothing's Gonna Stop Me Now"
        },
        "8": {
            "Artist": "Living In A Box",
            "Song": "Living In A Box"
        },
        "9": {
            "Artist": "Starship",
            "Song": "Nothing's Gonna Stop Us Now"
        },
        "10": {
            "Artist": "Madonna",
            "Song": "La isla bonita"
        }
    },
    "25": {
        "1": {
            "Artist": "Whitney Houston",
            "Song": "I Wanna Dance With Somebody (Who Loves Me)"
        },
        "2": {
            "Artist": "Johnny Logan",
            "Song": "Hold Me Now"
        },
        "3": {
            "Artist": "George Michael",
            "Song": "I Want Your Sex"
        },
        "4": {
            "Artist": "TNT",
            "Song": "10,000 Lovers (In One)"
        },
        "5": {
            "Artist": "Ferry Aid",
            "Song": "Let It Be"
        },
        "6": {
            "Artist": "Samantha Fox",
            "Song": "Nothing's Gonna Stop Me Now"
        },
        "7": {
            "Artist": "Madonna",
            "Song": "La isla bonita"
        },
        "8": {
            "Artist": "Living In A Box",
            "Song": "Living In A Box"
        },
        "9": {
            "Artist": "Mental As Anything",
            "Song": "Live It Up"
        },
        "10": {
            "Artist": "Johnny Hates Jazz",
            "Song": "Shattered Dreams"
        }
    },
    "26": {
        "1": {
            "Artist": "Whitney Houston",
            "Song": "I Wanna Dance With Somebody (Who Loves Me)"
        },
        "2": {
            "Artist": "TNT",
            "Song": "10,000 Lovers (In One)"
        },
        "3": {
            "Artist": "Johnny Logan",
            "Song": "Hold Me Now"
        },
        "4": {
            "Artist": "Samantha Fox",
            "Song": "Nothing's Gonna Stop Me Now"
        },
        "5": {
            "Artist": "George Michael",
            "Song": "I Want Your Sex"
        },
        "6": {
            "Artist": "Ferry Aid",
            "Song": "Let It Be"
        },
        "7": {
            "Artist": "Mental As Anything",
            "Song": "Live It Up"
        },
        "8": {
            "Artist": "Johnny Hates Jazz",
            "Song": "Shattered Dreams"
        },
        "9": {
            "Artist": "Madonna",
            "Song": "La isla bonita"
        },
        "10": {
            "Artist": "Living In A Box",
            "Song": "Living In A Box"
        }
    },
    "27": {
        "1": {
            "Artist": "Whitney Houston",
            "Song": "I Wanna Dance With Somebody (Who Loves Me)"
        },
        "2": {
            "Artist": "Samantha Fox",
            "Song": "Nothing's Gonna Stop Me Now"
        },
        "3": {
            "Artist": "TNT",
            "Song": "10,000 Lovers (In One)"
        },
        "4": {
            "Artist": "George Michael",
            "Song": "I Want Your Sex"
        },
        "5": {
            "Artist": "Johnny Logan",
            "Song": "Hold Me Now"
        },
        "6": {
            "Artist": "Johnny Hates Jazz",
            "Song": "Shattered Dreams"
        },
        "7": {
            "Artist": "Ole I'Dole",
            "Song": "This Town Ain't Big Enough For The Both Of Us"
        },
        "8": {
            "Artist": "Living In A Box",
            "Song": "Living In A Box"
        },
        "9": {
            "Artist": "Mental As Anything",
            "Song": "Live It Up"
        },
        "10": {
            "Artist": "Madonna",
            "Song": "La isla bonita"
        }
    },
    "28": {
        "1": {
            "Artist": "Whitney Houston",
            "Song": "I Wanna Dance With Somebody (Who Loves Me)"
        },
        "2": {
            "Artist": "a-ha",
            "Song": "The Living Daylights"
        },
        "3": {
            "Artist": "Samantha Fox",
            "Song": "Nothing's Gonna Stop Me Now"
        },
        "4": {
            "Artist": "TNT",
            "Song": "10,000 Lovers (In One)"
        },
        "5": {
            "Artist": "George Michael",
            "Song": "I Want Your Sex"
        },
        "6": {
            "Artist": "Johnny Hates Jazz",
            "Song": "Shattered Dreams"
        },
        "7": {
            "Artist": "Ole I'Dole",
            "Song": "This Town Ain't Big Enough For The Both Of Us"
        },
        "8": {
            "Artist": "Johnny Logan",
            "Song": "Hold Me Now"
        },
        "9": {
            "Artist": "Pet Shop Boys",
            "Song": "It's A Sin"
        },
        "10": {
            "Artist": "Mental As Anything",
            "Song": "Live It Up"
        }
    },
    "29": {
        "1": {
            "Artist": "a-ha",
            "Song": "The Living Daylights"
        },
        "2": {
            "Artist": "Samantha Fox",
            "Song": "Nothing's Gonna Stop Me Now"
        },
        "3": {
            "Artist": "Whitney Houston",
            "Song": "I Wanna Dance With Somebody (Who Loves Me)"
        },
        "4": {
            "Artist": "TNT",
            "Song": "10,000 Lovers (In One)"
        },
        "5": {
            "Artist": "Johnny Logan",
            "Song": "Hold Me Now"
        },
        "6": {
            "Artist": "Ole I'Dole",
            "Song": "This Town Ain't Big Enough For The Both Of Us"
        },
        "7": {
            "Artist": "George Michael",
            "Song": "I Want Your Sex"
        },
        "8": {
            "Artist": "Pet Shop Boys",
            "Song": "It's A Sin"
        },
        "9": {
            "Artist": "Crowded House",
            "Song": "Don't Dream It's Over"
        },
        "10": {
            "Artist": "Johnny Hates Jazz",
            "Song": "Shattered Dreams"
        }
    },
    "30": {
        "1": {
            "Artist": "a-ha",
            "Song": "The Living Daylights"
        },
        "2": {
            "Artist": "Pet Shop Boys",
            "Song": "It's A Sin"
        },
        "3": {
            "Artist": "Samantha Fox",
            "Song": "Nothing's Gonna Stop Me Now"
        },
        "4": {
            "Artist": "Madonna",
            "Song": "Who's That Girl"
        },
        "5": {
            "Artist": "Whitney Houston",
            "Song": "I Wanna Dance With Somebody (Who Loves Me)"
        },
        "6": {
            "Artist": "Ole I'Dole",
            "Song": "This Town Ain't Big Enough For The Both Of Us"
        },
        "7": {
            "Artist": "George Michael",
            "Song": "I Want Your Sex"
        },
        "8": {
            "Artist": "TNT",
            "Song": "10,000 Lovers (In One)"
        },
        "9": {
            "Artist": "Crowded House",
            "Song": "Don't Dream It's Over"
        },
        "10": {
            "Artist": "Mixed Emotions",
            "Song": "You Want Love (Maria, Maria...)"
        }
    },
    "31": {
        "1": {
            "Artist": "a-ha",
            "Song": "The Living Daylights"
        },
        "2": {
            "Artist": "Madonna",
            "Song": "Who's That Girl"
        },
        "3": {
            "Artist": "Pet Shop Boys",
            "Song": "It's A Sin"
        },
        "4": {
            "Artist": "Ole I'Dole",
            "Song": "This Town Ain't Big Enough For The Both Of Us"
        },
        "5": {
            "Artist": "Michael Jackson",
            "Song": "I Just Can't Stop Loving You"
        },
        "6": {
            "Artist": "Crowded House",
            "Song": "Don't Dream It's Over"
        },
        "7": {
            "Artist": "Glenn Medeiros",
            "Song": "Nothing's Gonna Change My Love For You"
        },
        "8": {
            "Artist": "Samantha Fox",
            "Song": "Nothing's Gonna Stop Me Now"
        },
        "9": {
            "Artist": "TNT",
            "Song": "10,000 Lovers (In One)"
        },
        "10": {
            "Artist": "Heart",
            "Song": "Alone"
        }
    },
    "32": {
        "1": {
            "Artist": "Michael Jackson",
            "Song": "I Just Can't Stop Loving You"
        },
        "2": {
            "Artist": "Pet Shop Boys",
            "Song": "It's A Sin"
        },
        "3": {
            "Artist": "a-ha",
            "Song": "The Living Daylights"
        },
        "4": {
            "Artist": "Madonna",
            "Song": "Who's That Girl"
        },
        "5": {
            "Artist": "Glenn Medeiros",
            "Song": "Nothing's Gonna Change My Love For You"
        },
        "6": {
            "Artist": "Ole I'Dole",
            "Song": "This Town Ain't Big Enough For The Both Of Us"
        },
        "7": {
            "Artist": "Crowded House",
            "Song": "Don't Dream It's Over"
        },
        "8": {
            "Artist": "Heart",
            "Song": "Alone"
        },
        "9": {
            "Artist": "Samantha Fox",
            "Song": "Nothing's Gonna Stop Me Now"
        },
        "10": {
            "Artist": "Mixed Emotions",
            "Song": "You Want Love (Maria, Maria...)"
        }
    },
    "33": {
        "1": {
            "Artist": "Michael Jackson",
            "Song": "I Just Can't Stop Loving You"
        },
        "2": {
            "Artist": "Pet Shop Boys",
            "Song": "It's A Sin"
        },
        "3": {
            "Artist": "Madonna",
            "Song": "Who's That Girl"
        },
        "4": {
            "Artist": "a-ha",
            "Song": "The Living Daylights"
        },
        "5": {
            "Artist": "Glenn Medeiros",
            "Song": "Nothing's Gonna Change My Love For You"
        },
        "6": {
            "Artist": "Crowded House",
            "Song": "Don't Dream It's Over"
        },
        "7": {
            "Artist": "Ole I'Dole",
            "Song": "This Town Ain't Big Enough For The Both Of Us"
        },
        "8": {
            "Artist": "Heart",
            "Song": "Alone"
        },
        "9": {
            "Artist": "Samantha Fox",
            "Song": "Nothing's Gonna Stop Me Now"
        },
        "10": {
            "Artist": "Johnny Hates Jazz",
            "Song": "Shattered Dreams"
        }
    },
    "34": {
        "1": {
            "Artist": "Michael Jackson",
            "Song": "I Just Can't Stop Loving You"
        },
        "2": {
            "Artist": "Pet Shop Boys",
            "Song": "It's A Sin"
        },
        "3": {
            "Artist": "Glenn Medeiros",
            "Song": "Nothing's Gonna Change My Love For You"
        },
        "4": {
            "Artist": "Madonna",
            "Song": "Who's That Girl"
        },
        "5": {
            "Artist": "a-ha",
            "Song": "The Living Daylights"
        },
        "6": {
            "Artist": "Ole I'Dole",
            "Song": "This Town Ain't Big Enough For The Both Of Us"
        },
        "7": {
            "Artist": "Heart",
            "Song": "Alone"
        },
        "8": {
            "Artist": "Crowded House",
            "Song": "Don't Dream It's Over"
        },
        "9": {
            "Artist": "Los Lobos",
            "Song": "La Bamba"
        },
        "10": {
            "Artist": "Freiheit",
            "Song": "Play It Cool"
        }
    },
    "35": {
        "1": {
            "Artist": "Michael Jackson",
            "Song": "I Just Can't Stop Loving You"
        },
        "2": {
            "Artist": "Glenn Medeiros",
            "Song": "Nothing's Gonna Change My Love For You"
        },
        "3": {
            "Artist": "Pet Shop Boys",
            "Song": "It's A Sin"
        },
        "4": {
            "Artist": "Madonna",
            "Song": "Who's That Girl"
        },
        "5": {
            "Artist": "Los Lobos",
            "Song": "La Bamba"
        },
        "6": {
            "Artist": "Heart",
            "Song": "Alone"
        },
        "7": {
            "Artist": "Crowded House",
            "Song": "Don't Dream It's Over"
        },
        "8": {
            "Artist": "a-ha",
            "Song": "The Living Daylights"
        },
        "9": {
            "Artist": "Ole I'Dole",
            "Song": "This Town Ain't Big Enough For The Both Of Us"
        },
        "10": {
            "Artist": "Spagna",
            "Song": "Call Me"
        }
    },
    "36": {
        "1": {
            "Artist": "Michael Jackson",
            "Song": "I Just Can't Stop Loving You"
        },
        "2": {
            "Artist": "Pet Shop Boys",
            "Song": "It's A Sin"
        },
        "3": {
            "Artist": "Glenn Medeiros",
            "Song": "Nothing's Gonna Change My Love For You"
        },
        "4": {
            "Artist": "Los Lobos",
            "Song": "La Bamba"
        },
        "5": {
            "Artist": "Heart",
            "Song": "Alone"
        },
        "6": {
            "Artist": "Madonna",
            "Song": "Who's That Girl"
        },
        "7": {
            "Artist": "Ole I'Dole",
            "Song": "This Town Ain't Big Enough For The Both Of Us"
        },
        "8": {
            "Artist": "Spagna",
            "Song": "Call Me"
        },
        "9": {
            "Artist": "a-ha",
            "Song": "The Living Daylights"
        },
        "10": {
            "Artist": "Freiheit",
            "Song": "Play It Cool"
        }
    },
    "37": {
        "1": {
            "Artist": "Michael Jackson",
            "Song": "I Just Can't Stop Loving You"
        },
        "2": {
            "Artist": "Pet Shop Boys",
            "Song": "It's A Sin"
        },
        "3": {
            "Artist": "Glenn Medeiros",
            "Song": "Nothing's Gonna Change My Love For You"
        },
        "4": {
            "Artist": "Spagna",
            "Song": "Call Me"
        },
        "5": {
            "Artist": "Heart",
            "Song": "Alone"
        },
        "6": {
            "Artist": "Desireless",
            "Song": "Voyage voyage"
        },
        "7": {
            "Artist": "Los Lobos",
            "Song": "La Bamba"
        },
        "8": {
            "Artist": "Madonna",
            "Song": "Who's That Girl"
        },
        "9": {
            "Artist": "Pet Shop Boys with Dusty Springfield",
            "Song": "What Have I Done To Deserve This?"
        },
        "10": {
            "Artist": "Ole I'Dole",
            "Song": "This Town Ain't Big Enough For The Both Of Us"
        }
    },
    "38": {
        "1": {
            "Artist": "Michael Jackson",
            "Song": "I Just Can't Stop Loving You"
        },
        "2": {
            "Artist": "Pet Shop Boys",
            "Song": "It's A Sin"
        },
        "3": {
            "Artist": "Glenn Medeiros",
            "Song": "Nothing's Gonna Change My Love For You"
        },
        "4": {
            "Artist": "Los Lobos",
            "Song": "La Bamba"
        },
        "5": {
            "Artist": "Desireless",
            "Song": "Voyage voyage"
        },
        "6": {
            "Artist": "The Monroes [NO]",
            "Song": "I Call It Love"
        },
        "7": {
            "Artist": "Spagna",
            "Song": "Call Me"
        },
        "8": {
            "Artist": "Heart",
            "Song": "Alone"
        },
        "9": {
            "Artist": "Pet Shop Boys with Dusty Springfield",
            "Song": "What Have I Done To Deserve This?"
        },
        "10": {
            "Artist": "Madonna",
            "Song": "Who's That Girl"
        }
    },
    "39": {
        "1": {
            "Artist": "Pet Shop Boys",
            "Song": "It's A Sin"
        },
        "2": {
            "Artist": "Michael Jackson",
            "Song": "Bad"
        },
        "3": {
            "Artist": "The Monroes [NO]",
            "Song": "I Call It Love"
        },
        "4": {
            "Artist": "Desireless",
            "Song": "Voyage voyage"
        },
        "5": {
            "Artist": "Los Lobos",
            "Song": "La Bamba"
        },
        "6": {
            "Artist": "Glenn Medeiros",
            "Song": "Nothing's Gonna Change My Love For You"
        },
        "7": {
            "Artist": "Michael Jackson",
            "Song": "I Just Can't Stop Loving You"
        },
        "8": {
            "Artist": "Spagna",
            "Song": "Call Me"
        },
        "9": {
            "Artist": "Heart",
            "Song": "Alone"
        },
        "10": {
            "Artist": "Rick Astley",
            "Song": "Never Gonna Give You Up"
        }
    },
    "40": {
        "1": {
            "Artist": "Desireless",
            "Song": "Voyage voyage"
        },
        "2": {
            "Artist": "Michael Jackson",
            "Song": "Bad"
        },
        "3": {
            "Artist": "Bruce Springsteen",
            "Song": "Brilliant Disguise"
        },
        "4": {
            "Artist": "Rick Astley",
            "Song": "Never Gonna Give You Up"
        },
        "5": {
            "Artist": "The Monroes [NO]",
            "Song": "I Call It Love"
        },
        "6": {
            "Artist": "Pet Shop Boys",
            "Song": "It's A Sin"
        },
        "7": {
            "Artist": "Spagna",
            "Song": "Call Me"
        },
        "8": {
            "Artist": "Heart",
            "Song": "Alone"
        },
        "9": {
            "Artist": "Los Lobos",
            "Song": "La Bamba"
        },
        "10": {
            "Artist": "Glenn Medeiros",
            "Song": "Nothing's Gonna Change My Love For You"
        }
    },
    "41": {
        "1": {
            "Artist": "Bruce Springsteen",
            "Song": "Brilliant Disguise"
        },
        "2": {
            "Artist": "Desireless",
            "Song": "Voyage voyage"
        },
        "3": {
            "Artist": "Rick Astley",
            "Song": "Never Gonna Give You Up"
        },
        "4": {
            "Artist": "The Monroes [NO]",
            "Song": "I Call It Love"
        },
        "5": {
            "Artist": "Michael Jackson",
            "Song": "Bad"
        },
        "6": {
            "Artist": "Los Lobos",
            "Song": "La Bamba"
        },
        "7": {
            "Artist": "Spagna",
            "Song": "Call Me"
        },
        "8": {
            "Artist": "Pet Shop Boys",
            "Song": "It's A Sin"
        },
        "9": {
            "Artist": "Glenn Medeiros",
            "Song": "Nothing's Gonna Change My Love For You"
        },
        "10": {
            "Artist": "Heart",
            "Song": "Alone"
        }
    },
    "42": {
        "1": {
            "Artist": "Bruce Springsteen",
            "Song": "Brilliant Disguise"
        },
        "2": {
            "Artist": "Desireless",
            "Song": "Voyage voyage"
        },
        "3": {
            "Artist": "Rick Astley",
            "Song": "Never Gonna Give You Up"
        },
        "4": {
            "Artist": "Michael Jackson",
            "Song": "Bad"
        },
        "5": {
            "Artist": "The Monroes [NO]",
            "Song": "I Call It Love"
        },
        "6": {
            "Artist": "Los Lobos",
            "Song": "La Bamba"
        },
        "7": {
            "Artist": "Spagna",
            "Song": "Call Me"
        },
        "8": {
            "Artist": "Heart",
            "Song": "Alone"
        },
        "9": {
            "Artist": "Glenn Medeiros",
            "Song": "Nothing's Gonna Change My Love For You"
        },
        "10": {
            "Artist": "deLillos",
            "Song": "S'il vous plaxeet"
        }
    },
    "43": {
        "1": {
            "Artist": "Rick Astley",
            "Song": "Never Gonna Give You Up"
        },
        "2": {
            "Artist": "Desireless",
            "Song": "Voyage voyage"
        },
        "3": {
            "Artist": "Bruce Springsteen",
            "Song": "Brilliant Disguise"
        },
        "4": {
            "Artist": "Michael Jackson",
            "Song": "Bad"
        },
        "5": {
            "Artist": "Spagna",
            "Song": "Call Me"
        },
        "6": {
            "Artist": "The Monroes [NO]",
            "Song": "I Call It Love"
        },
        "7": {
            "Artist": "Bee Gees",
            "Song": "You Win Again"
        },
        "8": {
            "Artist": "Heart",
            "Song": "Alone"
        },
        "9": {
            "Artist": "KISS",
            "Song": "Crazy Crazy Nights"
        },
        "10": {
            "Artist": "Madonna",
            "Song": "Causing A Commotion"
        }
    },
    "44": {
        "1": {
            "Artist": "Desireless",
            "Song": "Voyage voyage"
        },
        "2": {
            "Artist": "Rick Astley",
            "Song": "Never Gonna Give You Up"
        },
        "3": {
            "Artist": "Bee Gees",
            "Song": "You Win Again"
        },
        "4": {
            "Artist": "George Michael",
            "Song": "Faith"
        },
        "5": {
            "Artist": "Bruce Springsteen",
            "Song": "Brilliant Disguise"
        },
        "6": {
            "Artist": "Michael Jackson",
            "Song": "Bad"
        },
        "7": {
            "Artist": "Spagna",
            "Song": "Call Me"
        },
        "8": {
            "Artist": "The Monroes [NO]",
            "Song": "I Call It Love"
        },
        "9": {
            "Artist": "Eurythmics",
            "Song": "Beethoven"
        },
        "10": {
            "Artist": "Heart",
            "Song": "Alone"
        }
    },
    "45": {
        "1": {
            "Artist": "Bee Gees",
            "Song": "You Win Again"
        },
        "2": {
            "Artist": "Desireless",
            "Song": "Voyage voyage"
        },
        "3": {
            "Artist": "Rick Astley",
            "Song": "Never Gonna Give You Up"
        },
        "4": {
            "Artist": "George Michael",
            "Song": "Faith"
        },
        "5": {
            "Artist": "Bruce Springsteen",
            "Song": "Brilliant Disguise"
        },
        "6": {
            "Artist": "Sabrina",
            "Song": "Boys"
        },
        "7": {
            "Artist": "KISS",
            "Song": "Crazy Crazy Nights"
        },
        "8": {
            "Artist": "Eurythmics",
            "Song": "Beethoven"
        },
        "9": {
            "Artist": "Michael Jackson",
            "Song": "Bad"
        },
        "10": {
            "Artist": "Spagna",
            "Song": "Call Me"
        }
    },
    "46": {
        "1": {
            "Artist": "Bee Gees",
            "Song": "You Win Again"
        },
        "2": {
            "Artist": "Rick Astley",
            "Song": "Never Gonna Give You Up"
        },
        "3": {
            "Artist": "Desireless",
            "Song": "Voyage voyage"
        },
        "4": {
            "Artist": "George Michael",
            "Song": "Faith"
        },
        "5": {
            "Artist": "Sabrina",
            "Song": "Boys"
        },
        "6": {
            "Artist": "Eurythmics",
            "Song": "Beethoven"
        },
        "7": {
            "Artist": "KISS",
            "Song": "Crazy Crazy Nights"
        },
        "8": {
            "Artist": "Was (Not Was)",
            "Song": "Walk The Dinosaur"
        },
        "9": {
            "Artist": "Michael Jackson",
            "Song": "Bad"
        },
        "10": {
            "Artist": "Bananarama",
            "Song": "Love In The First Degree"
        }
    },
    "47": {
        "1": {
            "Artist": "Bee Gees",
            "Song": "You Win Again"
        },
        "2": {
            "Artist": "Desireless",
            "Song": "Voyage voyage"
        },
        "3": {
            "Artist": "George Michael",
            "Song": "Faith"
        },
        "4": {
            "Artist": "Rick Astley",
            "Song": "Never Gonna Give You Up"
        },
        "5": {
            "Artist": "Sabrina",
            "Song": "Boys"
        },
        "6": {
            "Artist": "Rick Astley",
            "Song": "Whenever You Need Somebody"
        },
        "7": {
            "Artist": "Was (Not Was)",
            "Song": "Walk The Dinosaur"
        },
        "8": {
            "Artist": "Eurythmics",
            "Song": "Beethoven"
        },
        "9": {
            "Artist": "KISS",
            "Song": "Crazy Crazy Nights"
        },
        "10": {
            "Artist": "Alexander O'Neal",
            "Song": "Criticize"
        }
    },
    "48": {
        "1": {
            "Artist": "Bee Gees",
            "Song": "You Win Again"
        },
        "2": {
            "Artist": "Rick Astley",
            "Song": "Whenever You Need Somebody"
        },
        "3": {
            "Artist": "Sabrina",
            "Song": "Boys"
        },
        "4": {
            "Artist": "Desireless",
            "Song": "Voyage voyage"
        },
        "5": {
            "Artist": "George Michael",
            "Song": "Faith"
        },
        "6": {
            "Artist": "Rick Astley",
            "Song": "Never Gonna Give You Up"
        },
        "7": {
            "Artist": "Was (Not Was)",
            "Song": "Walk The Dinosaur"
        },
        "8": {
            "Artist": "T'Pau",
            "Song": "China In Your Hand"
        },
        "9": {
            "Artist": "Ute Til Lunch",
            "Song": "Ute til lunsj"
        },
        "10": {
            "Artist": "Jørgen Slips",
            "Song": "Min Borghild"
        }
    },
    "49": {
        "1": {
            "Artist": "Bee Gees",
            "Song": "You Win Again"
        },
        "2": {
            "Artist": "Rick Astley",
            "Song": "Whenever You Need Somebody"
        },
        "3": {
            "Artist": "T'Pau",
            "Song": "China In Your Hand"
        },
        "4": {
            "Artist": "Sabrina",
            "Song": "Boys"
        },
        "5": {
            "Artist": "Ute Til Lunch",
            "Song": "Ute til lunsj"
        },
        "6": {
            "Artist": "George Michael",
            "Song": "Faith"
        },
        "7": {
            "Artist": "Was (Not Was)",
            "Song": "Walk The Dinosaur"
        },
        "8": {
            "Artist": "Desireless",
            "Song": "Voyage voyage"
        },
        "9": {
            "Artist": "Vanessa Paradis",
            "Song": "Joe le taxi"
        },
        "10": {
            "Artist": "KISS",
            "Song": "Crazy Crazy Nights"
        }
    },
    "50": {
        "1": {
            "Artist": "T'Pau",
            "Song": "China In Your Hand"
        },
        "2": {
            "Artist": "Bee Gees",
            "Song": "You Win Again"
        },
        "3": {
            "Artist": "Ute Til Lunch",
            "Song": "Ute til lunsj"
        },
        "4": {
            "Artist": "Rick Astley",
            "Song": "Whenever You Need Somebody"
        },
        "5": {
            "Artist": "Sabrina",
            "Song": "Boys"
        },
        "6": {
            "Artist": "Vanessa Paradis",
            "Song": "Joe le taxi"
        },
        "7": {
            "Artist": "George Michael",
            "Song": "Faith"
        },
        "8": {
            "Artist": "Was (Not Was)",
            "Song": "Walk The Dinosaur"
        },
        "9": {
            "Artist": "Foreigner",
            "Song": "Say You Will"
        },
        "10": {
            "Artist": "Desireless",
            "Song": "Voyage voyage"
        }
    },
    "51": {
        "1": {
            "Artist": "T'Pau",
            "Song": "China In Your Hand"
        },
        "2": {
            "Artist": "Ute Til Lunch",
            "Song": "Ute til lunsj"
        },
        "3": {
            "Artist": "Bee Gees",
            "Song": "You Win Again"
        },
        "4": {
            "Artist": "Rick Astley",
            "Song": "Whenever You Need Somebody"
        },
        "5": {
            "Artist": "Vanessa Paradis",
            "Song": "Joe le taxi"
        },
        "6": {
            "Artist": "Was (Not Was)",
            "Song": "Walk The Dinosaur"
        },
        "7": {
            "Artist": "Sabrina",
            "Song": "Boys"
        },
        "8": {
            "Artist": "Foreigner",
            "Song": "Say You Will"
        },
        "9": {
            "Artist": "George Michael",
            "Song": "Faith"
        },
        "10": {
            "Artist": "George Harrison",
            "Song": "Got My Mind Set On You"
        }
    },
    "52": {
        "1": {
            "Artist": "T'Pau",
            "Song": "China In Your Hand"
        },
        "2": {
            "Artist": "Ute Til Lunch",
            "Song": "Ute til lunsj"
        },
        "3": {
            "Artist": "Bee Gees",
            "Song": "You Win Again"
        },
        "4": {
            "Artist": "Foreigner",
            "Song": "Say You Will"
        },
        "5": {
            "Artist": "Rick Astley",
            "Song": "Whenever You Need Somebody"
        },
        "6": {
            "Artist": "Belinda Carlisle",
            "Song": "Heaven Is A Place On Earth"
        },
        "7": {
            "Artist": "Sabrina",
            "Song": "Boys"
        },
        "8": {
            "Artist": "Pet Shop Boys",
            "Song": "Always On My Mind"
        },
        "9": {
            "Artist": "Drama [NO]",
            "Song": "Take It Away"
        },
        "10": {
            "Artist": "George Michael",
            "Song": "Faith"
        }
    }
}